jupyterlog.py
jupyterlog-1.2.0.dist-info/licenses/LICENSE
jupyterlog-1.2.0.dist-info/METADATA
jupyterlog-1.2.0.dist-info/WHEEL
jupyterlog-1.2.0.dist-info/top_level.txt
jupyterlog-1.2.0.dist-info/RECORD
