Metadata-Version: 2.4
Name: jupyterlog
Version: 1.2.0
Summary: Setup Logging for Jupyter Notebook
Home-page: http://github.com/jupyterlog/jupyterlog
Author: Zhiqing Xiao
Author-email: xzq.xiaozhiqing@gmail.com
License: MIT
Classifier: Programming Language :: Python
License-File: LICENSE
Dynamic: author
Dynamic: author-email
Dynamic: classifier
Dynamic: description
Dynamic: description-content-type
Dynamic: home-page
Dynamic: license
Dynamic: license-file
Dynamic: summary
